CHANGELOG.rst
CONTRIBUTORS
LICENSE
MANIFEST.in
README.rst
requirements.txt
setup.cfg
setup.py
./CHANGELOG.rst
./Makefile
./NEWS.rst
./README.rst
./docs/Makefile
./docs/api_index.rst
./docs/development.rst
./docs/index.rst
./docs/manpage.isbg.rst
./docs/manpage.isbg_sa_unwrap.rst
docs/Makefile
docs/api_index.rst
docs/conf.py
docs/development.rst
docs/index.rst
docs/manpage.isbg.rst
docs/manpage.isbg_sa_unwrap.rst
docs/nitpick-exceptions
examples/batch_spam_check.sh
examples/batch_spam_learn.sh
examples/crontab.example
isbg/__init__.py
isbg/__main__.py
isbg/imaputils.py
isbg/isbg.py
isbg/sa_unwrap.py
isbg/secrets.py
isbg/spamproc.py
isbg/utils.py
isbg.egg-info/PKG-INFO
isbg.egg-info/SOURCES.txt
isbg.egg-info/dependency_links.txt
isbg.egg-info/entry_points.txt
isbg.egg-info/requires.txt
isbg.egg-info/top_level.txt
tests/test___main__.py
tests/test_imaputils.py
tests/test_isbg.py
tests/test_sa_unwrap.py
tests/test_secrets.py
tests/test_spamproc.py
tests/test_utils.py