Metadata-Version: 2.1
Name: isbg
Version: 2.3.0
Summary: a script that makes it easy to scan an IMAP inbox for spam usingSpamAssassin and get your spam moved to another folder.
Home-page: https://gitlab.com/isbg/isbg
Author: ISBG contributors (see CONTRIBUTORS file)
Author-email: isbg@python.org
License: GPLv3
Keywords: email imap spamassasin filter
Platform: UNKNOWN
Classifier: Development Status :: 5 - Production/Stable
Classifier: Environment :: Console
Classifier: Intended Audience :: System Administrators
Classifier: License :: OSI Approved :: GNU General Public License v3 (GPLv3)
Classifier: Programming Language :: Python
Classifier: Programming Language :: Python :: 3
Classifier: Topic :: Communications :: Email :: Post-Office :: IMAP
Classifier: Topic :: Communications :: Email :: Filters
Classifier: Topic :: Utilities
Provides-Extra: cchardet
Provides-Extra: chardet
